petstore_gaurav_compose_sdk/__init__.py
petstore_gaurav_compose_sdk/api_client.py
petstore_gaurav_compose_sdk/api_response.py
petstore_gaurav_compose_sdk/configuration.py
petstore_gaurav_compose_sdk/exceptions.py
petstore_gaurav_compose_sdk/py.typed
petstore_gaurav_compose_sdk/rest.py
petstore_gaurav_compose_sdk/api/__init__.py
petstore_gaurav_compose_sdk/api/pet_api.py
petstore_gaurav_compose_sdk/api/store_api.py
petstore_gaurav_compose_sdk/api/user_api.py
petstore_gaurav_compose_sdk/models/__init__.py
petstore_gaurav_compose_sdk/models/address.py
petstore_gaurav_compose_sdk/models/api_response.py
petstore_gaurav_compose_sdk/models/category.py
petstore_gaurav_compose_sdk/models/customer.py
petstore_gaurav_compose_sdk/models/order.py
petstore_gaurav_compose_sdk/models/pet.py
petstore_gaurav_compose_sdk/models/tag.py
petstore_gaurav_compose_sdk/models/user.py
petstore_gaurav_compose_sdk-1.0.0.dist-info/METADATA
petstore_gaurav_compose_sdk-1.0.0.dist-info/WHEEL
petstore_gaurav_compose_sdk-1.0.0.dist-info/top_level.txt
petstore_gaurav_compose_sdk-1.0.0.dist-info/RECORD
